setup.py
JovyTesting/__init__.py
JovyTesting.egg-info/PKG-INFO
JovyTesting.egg-info/SOURCES.txt
JovyTesting.egg-info/dependency_links.txt
JovyTesting.egg-info/requires.txt
JovyTesting.egg-info/top_level.txt
JovyTesting/jmath/__init__.py
JovyTesting/qoutes/__init__.py
JovyTesting/shop/__init__.py