Metadata-Version: 1.0
Name: JovyTesting
Version: 0.2.9
Summary: The testing package for Jomy
Home-page: UNKNOWN
Author: Muheko Nikolas
Author-email: UNKNOWN
License: UNKNOWN
Platform: UNKNOWN
